plain/email/CHANGELOG.md
plain/email/README.md
plain/email/__init__.py
plain/email/default_settings.py
plain/email/message.py
plain/email/utils.py
plain/email/backends/__init__.py
plain/email/backends/base.py
plain/email/backends/console.py
plain/email/backends/filebased.py
plain/email/backends/smtp.py
plain_email-0.15.0.dist-info/METADATA
plain_email-0.15.0.dist-info/WHEEL
plain_email-0.15.0.dist-info/licenses/LICENSE
plain_email-0.15.0.dist-info/RECORD
