Metadata-Version: 2.4
Name: plain.email
Version: 0.15.0
Summary: Everything you need to send email in Plain.
Author-email: Dave Gaeddert <dave.gaeddert@dropseed.dev>
License-Expression: BSD-3-Clause
License-File: LICENSE
Requires-Python: >=3.13
Requires-Dist: plain<1.0.0
